cybrid_api_id/__init__.py
cybrid_api_id/api_client.py
cybrid_api_id/configuration.py
cybrid_api_id/exceptions.py
cybrid_api_id/model_utils.py
cybrid_api_id/rest.py
cybrid_api_id/api/__init__.py
cybrid_api_id/api/bank_applications_idp_api.py
cybrid_api_id/api/customer_tokens_idp_api.py
cybrid_api_id/api/organization_applications_idp_api.py
cybrid_api_id/api/users_idp_api.py
cybrid_api_id/apis/__init__.py
cybrid_api_id/model/__init__.py
cybrid_api_id/model/application.py
cybrid_api_id/model/application_list.py
cybrid_api_id/model/application_with_secret.py
cybrid_api_id/model/application_with_secret_all_of.py
cybrid_api_id/model/customer_token.py
cybrid_api_id/model/error_response.py
cybrid_api_id/model/list_request_page.py
cybrid_api_id/model/list_request_per_page.py
cybrid_api_id/model/patch_user.py
cybrid_api_id/model/post_bank_application.py
cybrid_api_id/model/post_customer_token.py
cybrid_api_id/model/post_organization_application.py
cybrid_api_id/model/post_user.py
cybrid_api_id/model/user.py
cybrid_api_id/model/user_list.py
cybrid_api_id/models/__init__.py
cybrid_api_id_python-0.126.83.dist-info/METADATA
cybrid_api_id_python-0.126.83.dist-info/WHEEL
cybrid_api_id_python-0.126.83.dist-info/top_level.txt
cybrid_api_id_python-0.126.83.dist-info/RECORD
