Metadata-Version: 2.4
Name: cybrid-api-id-python
Version: 0.126.83
Summary: Cybrid Identity API
Home-page: https://github.com/Cybrid-app/cybrid-api-id-python/
Author: Cybrid Support
Author-email: support@cybrid.app
License: Apache-2.0
Keywords: Cybrid Identity API
Requires-Python: >=3.6
Requires-Dist: urllib3>=1.25.3
Requires-Dist: python-dateutil
Dynamic: author
Dynamic: author-email
Dynamic: description
Dynamic: description-content-type
Dynamic: home-page
Dynamic: keywords
Dynamic: license
Dynamic: requires-dist
Dynamic: requires-python
Dynamic: summary
